etc/init.d/f5-oslbaasv2-agent
etc/neutron/services/f5/f5-openstack-agent.ini
etc/neutron/services/f5/esd/demo.json
f5_openstack_agent/__init__.py
f5_openstack_agent/lbaasv2/__init__.py
f5_openstack_agent/lbaasv2/drivers/__init__.py
f5_openstack_agent/lbaasv2/drivers/bigip/__init__.py
f5_openstack_agent/lbaasv2/drivers/bigip/agent.py
f5_openstack_agent/lbaasv2/drivers/bigip/agent_manager.py
f5_openstack_agent/lbaasv2/drivers/bigip/barbican_cert.py
f5_openstack_agent/lbaasv2/drivers/bigip/cluster_manager.py
f5_openstack_agent/lbaasv2/drivers/bigip/constants_v2.py
f5_openstack_agent/lbaasv2/drivers/bigip/esd_filehandler.py
f5_openstack_agent/lbaasv2/drivers/bigip/exceptions.py
f5_openstack_agent/lbaasv2/drivers/bigip/fdb_connector.py
f5_openstack_agent/lbaasv2/drivers/bigip/fdb_connector_ml2.py
f5_openstack_agent/lbaasv2/drivers/bigip/icontrol_driver.py
f5_openstack_agent/lbaasv2/drivers/bigip/l2_service.py
f5_openstack_agent/lbaasv2/drivers/bigip/l3_binding.py
f5_openstack_agent/lbaasv2/drivers/bigip/l7policy_adapter.py
f5_openstack_agent/lbaasv2/drivers/bigip/l7policy_builder.py
f5_openstack_agent/lbaasv2/drivers/bigip/l7policy_service.py
f5_openstack_agent/lbaasv2/drivers/bigip/lbaas_builder.py
f5_openstack_agent/lbaasv2/drivers/bigip/lbaas_driver.py
f5_openstack_agent/lbaasv2/drivers/bigip/lbaas_service.py
f5_openstack_agent/lbaasv2/drivers/bigip/listener_adapter.py
f5_openstack_agent/lbaasv2/drivers/bigip/listener_service.py
f5_openstack_agent/lbaasv2/drivers/bigip/loadbalancer_service.py
f5_openstack_agent/lbaasv2/drivers/bigip/network_helper.py
f5_openstack_agent/lbaasv2/drivers/bigip/network_service.py
f5_openstack_agent/lbaasv2/drivers/bigip/plugin_rpc.py
f5_openstack_agent/lbaasv2/drivers/bigip/pool_service.py
f5_openstack_agent/lbaasv2/drivers/bigip/resource_helper.py
f5_openstack_agent/lbaasv2/drivers/bigip/selfips.py
f5_openstack_agent/lbaasv2/drivers/bigip/service_adapter.py
f5_openstack_agent-10.1.0.dist-info/DESCRIPTION.rst
f5_openstack_agent-10.1.0.dist-info/METADATA
f5_openstack_agent-10.1.0.dist-info/RECORD
f5_openstack_agent-10.1.0.dist-info/WHEEL
f5_openstack_agent-10.1.0.dist-info/entry_points.txt
f5_openstack_agent-10.1.0.dist-info/metadata.json
f5_openstack_agent-10.1.0.dist-info/top_level.txt
