Metadata-Version: 2.0
Name: f5-openstack-agent
Version: 10.1.0
Summary: F5 Networks Agent for OpenStack services
Home-page: UNKNOWN
Author: F5 Networks
Author-email: f5_openstack_agent@f5.com
License: Apache License, Version 2.0
Platform: UNKNOWN
Classifier: Environment :: OpenStack
Classifier: Intended Audience :: Information Technology
Classifier: Intended Audience :: System Administrators
Classifier: License :: OSI Approved :: Apache Software License
Classifier: Operating System :: POSIX :: Linux
Classifier: Programming Language :: Python
Classifier: Programming Language :: Python :: 2
Classifier: Programming Language :: Python :: 2.7
Requires-Dist: f5-sdk (==2.3.3)
